[
    {
        "name": "Padfoot",
        "animal_type": "Dog",
        "gender": "Male",
        "age": "5",
        "weight": "75",
        "acquisition_date": "2025-05-04",
        "acquisition_country": "USA",
        "training_status": "In Training",
        "reserved": "No",
        "in_service_country": "USA",
        "breed": "Doodle"
    },
    {
        "name": "Luna",
        "animal_type": "Dog",
        "gender": "Female",
        "age": "8",
        "weight": "80",
        "acquisition_date": "2025-05-04",
        "acquisition_country": "USA",
        "training_status": "Fully Trained",
        "reserved": "Yes",
        "in_service_country": "USA",
        "breed": "Doodle"
    },
    {
        "name": "Pepper",
        "animal_type": "Dog",
        "gender": "Female",
        "age": "6",
        "weight": "85",
        "acquisition_date": "2025-05-04",
        "acquisition_country": "USA",
        "training_status": "Fully Trained",
        "reserved": "Yes",
        "in_service_country": "USA",
        "breed": "Newfoundland"
    }
]